{
  "list": [
    {
      "id": 1,
      "type": "徒步",
      "site": "哈科",
      "city": "Hake",
      "categroy": "walk",
      "imgUrl": "https://a0.muscache.com/im/pictures/46a95cc3-845b-4984-b2b6-b84b2e633951.jpg?aki_policy=large",
      "title": "10 Hidden Waterfalls w/ Local Cuisine",
      "price": 523,
      "star": 5,
      "comment": 105,
      "highPress": true
    },
    {
      "id": 2,
      "type": "一日游",
      "site": "里斯本",
      "city": "Libenshi",
      "categroy": "walk",
      "imgUrl": "https://a0.muscache.com/im/pictures/73d81f12-c386-4c73-a1f0-d25049f88f16.jpg?aki_policy=large",
      "title": "This is Sintra - a DAY to Remember!",
      "price": 483,
      "star": 5,
      "comment": 514,
      "highPress": true
    },
    {
      "id": 3,
      "type": "工作坊",
      "site": "北京",
      "city": "Beijing",
      "categroy": "art",
      "imgUrl": "https://a0.muscache.com/im/pictures/a98ad4bf-4329-4353-8cd4-68c96f4367f3.jpg?aki_policy=large",
      "title": "来老北京胡同里亲自体验有3000多年历史的古老篆刻艺术吧~地道又有趣儿",
      "price": 219,
      "star": 5,
      "comment": 293,
      "highPress": true
    },
    {
      "id": 4,
      "type": "野生动物",
      "site": "克萨达(Quesada)",
      "city": "Quesada",
      "categroy": "walk",
      "imgUrl": "https://a0.muscache.com/im/pictures/ae0520e7-243a-4698-b828-0eaed1b58ad3.jpg?aki_policy=large",
      "title": "Experiencia con el Oso Perezoso",
      "price": 171,
      "star": 5,
      "comment": 433,
      "highPress": true
    },
    {
      "id": 5,
      "type": "徒步",
      "site": "吉隆坡",
      "city": "Gerlongpo",
      "categroy": "walk",
      "imgUrl": "https://a0.muscache.com/im/pictures/75c6abbf-9b9e-440b-b003-f80329afd72f.jpg?aki_policy=large",
      "title": "2 Hidden Waterfalls + BatuCaves 5hours",
      "price": 253,
      "star": 5,
      "comment": 276,
      "highPress": true
    },
    {
      "id": 6,
      "type": "摄影艺术",
      "site": "锡拉",
      "city": "Sila",
      "categroy": "photo",
      "imgUrl": "https://a0.muscache.com/im/pictures/910de248-2375-432d-a219-2d6a770efddb.jpg?aki_policy=large",
      "title": "Santorini Photo Shoot",
      "price": 934,
      "star": 5,
      "comment": 60,
      "highPress": true
    },
    {
      "id": 7,
      "type": "历史漫步",
      "site": "德里",
      "city": "Deli",
      "categroy": "walk",
      "imgUrl": "https://a0.muscache.com/im/pictures/1b37342c-24f8-4440-b47a-017f147651fa.jpg?aki_policy=large",
      "title": "Hidden Gems of Old Delhi",
      "price": 276,
      "star": 5,
      "comment": 223,
      "highPress": true
    },
    {
      "id": 8,
      "type": "邂逅动物",
      "site": "西雅图",
      "city": "Siyatu",
      "categroy": "walk",
      "imgUrl": "https://a0.muscache.com/im/pictures/a7e59c75-a34d-4964-81e4-894e9b6afa66.jpg?aki_policy=large",
      "title": "Wolf Encounter",
      "price": 1385,
      "star": 5,
      "comment": 1784,
      "highPress": true
    },
    {
      "id": 68,
      "type": "摄影",
      "site": "纽约",
      "city": "Newyork",
      "categroy": "photo",
      "imgUrl": "https://z1.muscache.cn/im/pictures/20318d8b-f72b-4193-8f9c-1ac2e97e80de.jpg?aki_policy=large",
      "title": "PHOTOSHOOT WITH VIEW - NY BEST ROOFTOP",
      "price": 616,
      "star": 5,
      "comment": 78,
      "highPress": false
    },
    {
      "id": 69,
      "type": "摄影艺术",
      "site": "京都",
      "city": "Keyto",
      "categroy": "photo",
      "imgUrl": "https://z1.muscache.cn/im/pictures/2dbfc092-e6f1-4b79-b452-914983835ff9.jpg?aki_policy=large",
      "title": "Wol",
      "price": 375,
      "star": 5,
      "comment": 179,
      "highPress": false
    },
    {
      "id": 70,
      "type": "文化漫步 ",
      "site": "成都",
      "city": "Chengdu",
      "categroy": "walk",
      "imgUrl": "https://z1.muscache.cn/im/pictures/01766548-90cb-4545-8818-0585caa732c1.jpg?aki_policy=large",
      "title": "【VIPTour】在摄影圣地鸳鸯楼拍下最美照片＆老川大人给你",
      "price": 258,
      "star": 5,
      "comment": 89,
      "highPress": true
    },
    {
      "id": 71,
      "type": "文化漫步 ",
      "site": "上海",
      "city": "Shanghai",
      "categroy": "walk",
      "imgUrl": "https://z1.muscache.cn/im/pictures/9832e17e-5c1f-4b35-a0cb-ff6aab6de5c0.jpg?aki_policy=poster",
      "title": "法式风情｜上海老城早午餐与隐秘探店",
      "price": 99,
      "star": 5,
      "comment": 247,
      "highPress": false
    },
    {
      "id": 72,
      "type": "烘焙 ",
      "site": "上海",
      "city": "Shanghai",
      "categroy": "cate",
      "imgUrl": "https://z1.muscache.cn/im/pictures/9de08c11-a90f-48b6-a054-8bd83fe645c1.jpg?aki_policy=poster",
      "title": "在老上海洋房里，烘焙小白也能做出超fancy的星球蛋糕",
      "price": 380,
      "star": 5,
      "comment": 1,
      "highPress": false
    },
    {
      "id": 73,
      "type": "艺术漫步 ",
      "site": "上海",
      "city": "Shanghai",
      "categroy": "walk",
      "imgUrl": "https://z1.muscache.cn/im/pictures/ba30ad61-7960-43af-a72d-64e002e5ae43.jpg?aki_policy=poster",
      "title": "那些你不曾去过的外滩背后",
      "price": 298,
      "star": 5,
      "comment": 6,
      "highPress": false
    },
    {
      "id": 74,
      "type": "摄影 ",
      "site": "上海",
      "city": "Shanghai",
      "categroy": "photo",
      "imgUrl": "https://z1.muscache.cn/im/pictures/1637f8f0-8e12-4806-bb63-bb5d6112d984.jpg?aki_policy=poster",
      "title": "上海风情 | 旅拍摄影人镜头下的上海美食和小众展览",
      "price": 148,
      "star": 5,
      "comment": 89,
      "highPress": false
    },
    {
      "id": 75,
      "type": "工作坊 ",
      "site": "上海",
      "city": "Shanghai",
      "categroy": "workshop",
      "imgUrl": "https://z1.muscache.cn/im/pictures/aa13e7da-010c-4f2a-8b34-cd658d5b7ce8.jpg?aki_policy=poster",
      "title": "法租界里的法式花艺课\n",
      "price": 320,
      "star": 5,
      "comment": 14,
      "highPress": false
    },
    {
      "id": 76,
      "type": "摄影 ",
      "site": "上海",
      "city": "Shanghai",
      "categroy": "photo",
      "imgUrl": "https://z1.muscache.cn/im/pictures/8ad59fe1-b247-4468-b052-b14853013bb7.jpg?aki_policy=poster",
      "title": "一对一/最上海的专属人像旅拍",
      "price": 499,
      "star": 5,
      "comment": 34,
      "highPress": false
    },
    {
      "id": 77,
      "type": "摄影艺术 ",
      "site": "上海",
      "city": "Shanghai",
      "categroy": "photo",
      "imgUrl": "https://z1.muscache.cn/im/pictures/510f68c2-a07d-4a2f-9af1-fc2c99392058.jpg?aki_policy=poster",
      "title": "一场未知的胶片摄影之旅",
      "price": 298,
      "star": 5,
      "comment": 123,
      "highPress": false
    },
    {
      "id": 78,
      "type": "烹饪课",
      "site": "上海",
      "city": "Shanghai",
      "categroy": "cate",
      "imgUrl": "https://z1.muscache.cn/im/pictures/307a2dfe-9ed7-4aa5-b3d8-d6199c8a8fb0.jpg?aki_policy=poster",
      "title": "学做小笼包",
      "price": 346,
      "star": 5,
      "comment": 387,
      "highPress": false
    },
    {
      "id": 79,
      "type": "艺术工作坊",
      "site": "上海",
      "city": "Shanghai",
      "categroy": "workshop",
      "imgUrl": "https://z1.muscache.cn/im/pictures/b0735762-e097-4208-b1bf-356cb125c754.jpg?aki_policy=poster",
      "title": "无拘束的画画创作体验",
      "price": 39,
      "star": 5,
      "comment": 15,
      "highPress": false
    },
    {
      "id": 80,
      "type": "烘焙",
      "site": "上海",
      "city": "Shanghai",
      "categroy": "cate",
      "imgUrl": "https://z1.muscache.cn/im/pictures/e20d9961-1193-473c-b016-52583dbb551a.jpg?aki_policy=poster",
      "title": "弄堂里跟着法国蓝带毕业的老师做纯正可颂面包",
      "price": 198,
      "star": 5,
      "comment": 210,
      "highPress": false
    },
    {
      "id": 81,
      "type": "烹饪课 ",
      "site": "上海",
      "city": "Shanghai",
      "categroy": "cate",
      "imgUrl": "https://z1.muscache.cn/im/pictures/a377f5bf-bec2-4c81-bf1d-d7a48cabc861.jpg?aki_policy=poster",
      "title": "学做传统生煎包",
      "price": 298,
      "star": 5,
      "comment": 14,
      "highPress": false
    },
    {
      "id": 82,
      "type": "历史漫步 ",
      "site": "上海",
      "city": "Shanghai",
      "categroy": "walk",
      "imgUrl": "https://z1.muscache.cn/im/pictures/d0aa90cc-b455-4df9-9b6e-a53c61c2ecf3.jpg?aki_policy=poster",
      "title": "城市追溯--犹太上海人",
      "price": 298,
      "star": 5,
      "comment": 18,
      "highPress": false
    },
    {
      "id": 83,
      "type": "艺术工作坊 ",
      "site": "上海",
      "city": "Shanghai",
      "categroy": "art",
      "imgUrl": "https://z1.muscache.cn/im/pictures/d9192340-c715-43e6-af3e-a2dc114e9555.jpg?aki_policy=poster",
      "title": "把东方明珠装进画里",
      "price": 288,
      "star": 5,
      "comment": 14,
      "highPress": false
    },
    {
      "id": 84,
      "type": "摄影艺术 ",
      "site": "上海",
      "city": "Shanghai",
      "categroy": "photo",
      "imgUrl": "https://z1.muscache.cn/im/pictures/6a53ad9b-52cd-422c-a1be-c60475f20741.jpg?aki_policy=poster",
      "title": "（口碑超赞的旅拍）旅拍摄影师带你边逛边吃边拍体验上海味道",
      "price": 158,
      "star": 5,
      "comment": 16,
      "highPress": false
    },
    {
      "id": 85,
      "type": "摄影 ",
      "site": "上海",
      "city": "Shanghai",
      "categroy": "photo",
      "imgUrl": "https://z1.muscache.cn/im/pictures/0a03a979-f271-435c-84df-31672b355252.jpg?aki_policy=poster",
      "title": "上海 | 自然系胶片写真",
      "price": 399,
      "star": 5,
      "comment": 47,
      "highPress": false
    },
    {
      "id": 86,
      "type": "品尝美食 ",
      "site": "上海",
      "city": "Shanghai",
      "categroy": "cate",
      "imgUrl": "https://z1.muscache.cn/im/pictures/78123001-1808-46f0-9956-58e5b60a75e5.jpg?aki_policy=poster",
      "title": "上海妈妈的家常菜",
      "price": 335,
      "star": 5,
      "comment": 10,
      "highPress": false
    },
    {
      "id": 87,
      "type": "摄影艺术 ",
      "site": "上海",
      "city": "Shanghai",
      "categroy": "photo",
      "imgUrl": "https://z1.muscache.cn/im/pictures/a769e104-8a27-4ca1-ab0e-6b6cbff7cf5f.jpg?aki_policy=poster",
      "title": "魔都天际线下的手机光影艺术之旅",
      "price": 298,
      "star": 5,
      "comment": 89,
      "highPress": false
    },
    {
      "id": 88,
      "type": "音乐课 ",
      "site": "上海",
      "city": "Shanghai",
      "categroy": "music",
      "imgUrl": "https://z1.muscache.cn/im/pictures/65c45e9d-b272-4d27-ade2-886393bf7ef1.jpg?aki_policy=poster",
      "title": "音乐人带你速成尤克里里弹唱,体验最IN音乐现场",
      "price": 168,
      "star": 5,
      "comment": 89,
      "highPress": false
    },
    {
      "id": 91,
      "type": "摄影艺术",
      "site": "杭州",
      "city": "Hangzhou",
      "categroy": "photo",
      "imgUrl": "https://z1.muscache.cn/im/pictures/f36a10fe-cd06-4d7b-9afb-22c54cfec432.jpg?aki_policy=poster",
      "title": "打卡杭州小众拍照地点一小时体验",
      "price": 81,
      "star": 5,
      "comment": 10,
      "highPress": false
    },
    {
      "id": 92,
      "type": "摄影",
      "site": "杭州",
      "city": "Hangzhou",
      "categroy": "photo",
      "imgUrl": "https://z1.muscache.cn/im/pictures/f23fce09-83c8-4530-ac04-d32d862e05cd.jpg?aki_policy=poster",
      "title": "摄影师带你游杭州，用镜头记录你的一天",
      "price": 78,
      "star": 5,
      "comment": 48,
      "highPress": false
    },
    {
      "id": 93,
      "type": "探索美食",
      "site": "杭州",
      "city": "Hangzhou",
      "categroy": "cate",
      "imgUrl": "https://z1.muscache.cn/im/pictures/9796ab86-a6be-4e8a-879d-902c8b81f5fe.jpg?aki_policy=poster",
      "title": "寻味杭州——带你吃地道的杭州，游古老的钱塘",
      "price": 258,
      "star": 5,
      "comment": 48,
      "highPress": false
    },
    {
      "id": 94,
      "type": "摄影艺术",
      "site": "杭州",
      "city": "Hangzhou",
      "categroy": "photo",
      "imgUrl": "https://z1.muscache.cn/im/pictures/ff6b4ebc-d59f-489c-b21c-235ad5fdeabf.jpg?aki_policy=poster",
      "title": "【深度西湖】 体验远离人潮的静谧杭州/旅拍摄影/避世小众/打卡网红古风地标",
      "price": 358,
      "star": 5,
      "comment": 7,
      "highPress": false
    },
    {
      "id": 95,
      "type": "工作坊",
      "site": "杭州",
      "city": "Hangzhou",
      "categroy": "workshop",
      "imgUrl": "https://z1.muscache.cn/im/pictures/7d591295-e129-4765-832e-f40a02347db7.jpg?aki_policy=poster",
      "title": "自在坞手工文艺复兴(陶艺）",
      "price": 258,
      "star": 5,
      "comment": 89,
      "highPress": false
    },
    {
      "id": 96,
      "type": "音乐课",
      "site": "杭州",
      "city": "Hangzhou",
      "categroy": "music",
      "imgUrl": "https://z1.muscache.cn/im/pictures/e6dd4d2a-5f7a-439e-ab1b-0c344685cc40.jpg?aki_policy=poster",
      "title": "「Everything is rhythm」倾听自己的声音@西非曼丁音乐王国",
      "price": 358,
      "star": 5,
      "comment": 19,
      "highPress": false
    },
    {
      "id": 97,
      "type": "文化漫步",
      "site": "杭州",
      "city": "Hangzhou",
      "categroy": "photo",
      "imgUrl": "https://z1.muscache.cn/im/pictures/95c88d3b-4212-4333-a900-de6161fda824.jpg?aki_policy=poster",
      "title": "市井杭州半日闲",
      "price": 258,
      "star": 5,
      "comment": 1,
      "highPress": false
    },
    {
      "id": 98,
      "type": "音乐课",
      "site": "杭州",
      "city": "Hangzhou",
      "categroy": "music",
      "imgUrl": "https://z1.muscache.cn/im/pictures/9ee8ff94-59a1-4571-855d-c676c4a276d0.jpg?aki_policy=poster",
      "title": "日本器乐探秘之旅",
      "price": 258,
      "star": 5,
      "comment": 89,
      "highPress": false
    },
    {
      "id": 99,
      "type": "户外漫步",
      "site": "杭州",
      "city": "Hangzhou",
      "categroy": "nature",
      "imgUrl": "https://z1.muscache.cn/im/pictures/76489237-678a-428e-aff6-42f0946a21ee.jpg?aki_policy=poster",
      "title": "西湖畔体验尺八的千年古韵",
      "price": 358,
      "star": 5,
      "comment": 19,
      "highPress": false
    },
    {
      "id": 100,
      "type": "艺术工作坊",
      "site": "杭州",
      "city": "Hangzhou",
      "categroy": "workshop",
      "imgUrl": "https://z1.muscache.cn/im/pictures/9bfdc0a7-bd10-4fa1-ae98-43d3e6c8f4bd.jpg?aki_policy=poster",
      "title": "你",
      "price": 258,
      "star": 5,
      "comment": 89,
      "highPress": false
    },
    {
      "id": 101,
      "type": "大自然 ",
      "site": "杭州",
      "city": "Hangzhou",
      "categroy": "nature",
      "imgUrl": "https://z1.muscache.cn/im/pictures/8a9fbb39-39c5-4391-b225-34528087a168.jpg?aki_policy=poster",
      "title": "杭州湖山闲茶",
      "price": 258,
      "star": 5,
      "comment": 89,
      "highPress": false
    },
    {
      "id": 102,
      "type": "工作坊 ",
      "site": "杭州",
      "city": "Hangzhou",
      "categroy": "workshop",
      "imgUrl": "https://z1.muscache.cn/im/pictures/1d7f29e6-2728-4124-bebb-b4fb32c63f93.jpg?aki_policy=poster",
      "title": "自在坞手工文艺复兴（玻璃马赛克）",
      "price": 258,
      "star": 5,
      "comment": 89,
      "highPress": false
    },
    {
      "id": 103,
      "type": "品茶 ",
      "site": "杭州",
      "city": "Hangzhou",
      "categroy": "workshop",
      "imgUrl": "https://z1.muscache.cn/im/pictures/c63df26a-a614-498e-b6e6-fb20f5017f81.jpg?aki_policy=poster",
      "title": "龙坞茶镇里的龙井茶采制体验",
      "price": 258,
      "star": 5,
      "comment": 89,
      "highPress": false
    },
    {
      "id": 104,
      "type": "逛酒吧 ",
      "site": "杭州",
      "city": "Hangzhou",
      "categroy": "nightLife",
      "imgUrl": "https://z1.muscache.cn/im/pictures/eca9aee2-6df1-4f92-9ac8-14e409fb0be8.jpg?aki_policy=poster",
      "title": "Uncover Secret Laneway Bars",
      "price": 258,
      "star": 5,
      "comment": 89,
      "highPress": false
    },
    {
      "id": 105,
      "type": "一日游 ",
      "site": "杭州",
      "city": "Hangzhou",
      "categroy": "nature",
      "imgUrl": "https://z1.muscache.cn/im/pictures/b9e438c8-0ad9-413e-a1f4-3b263bc6a8ec.jpg?aki_policy=poster",
      "title": "动情山水 · 静心问禅",
      "price": 258,
      "star": 5,
      "comment": 89,
      "highPress": false
    },
    {
      "id": 106,
      "type": "摄影艺术 ",
      "site": "杭州",
      "city": "Hangzhou",
      "categroy": "photo",
      "imgUrl": "https://z1.muscache.cn/im/pictures/e6c05d2b-ad0d-4885-a1f1-444c2cc800e5.jpg?aki_policy=poster",
      "title": "禅意旅行，带你体验杭州佛系style",
      "price": 258,
      "star": 5,
      "comment": 89,
      "highPress": false
    },
    {
      "id": 107,
      "type": "参观农场 ",
      "site": "杭州",
      "city": "Hangzhou",
      "categroy": "nature",
      "imgUrl": "https://z1.muscache.cn/im/pictures/827a5247-a942-43aa-a956-97d08f891c54.jpg?aki_policy=poster",
      "title": "碧螺春的故乡洞庭西山采茶做茶品茶，体验一杯茶的诞生",
      "price": 258,
      "star": 5,
      "comment": 89,
      "highPress": false
    },
    {
      "id": 108,
      "type": "工作坊 ",
      "site": "杭州",
      "city": "Hangzhou",
      "categroy": "cate",
      "imgUrl": "https://z1.muscache.cn/im/pictures/afa058f5-c41c-491a-b66c-2cbe75bbadb2.jpg?aki_policy=poster",
      "title": "精品咖啡入门及初级冲煮技术",
      "price": 258,
      "star": 5,
      "comment": 89,
      "highPress": false
    }
  ]
}
